{"cameraMode":{"drawMode":0,"name":"Shaded","section":"Shading Mode"},"sceneLighting":true,"audioPlay":false,"sceneViewState":{"m_AlwaysRefresh":false,"showFog":true,"showSkybox":true,"showFlares":true,"showImageEffects":true,"showParticleSystems":true,"showVisualEffectGraphs":true,"m_FxEnabled":true},"in2DMode":false,"pivot":{"x":81.39523315429688,"y":74.63948059082031,"z":71.63681030273438},"rotation":{"x":0.18385133147239686,"y":0.382032573223114,"z":-0.07783970236778259,"w":0.9023343920707703},"size":157.59414672851563,"orthographic":false}